MANIFEST.in
README.txt
collective.linkedin-configure.zcml
setup.cfg
setup.py
collective/__init__.py
collective.linkedin.egg-info/PKG-INFO
collective.linkedin.egg-info/SOURCES.txt
collective.linkedin.egg-info/dependency_links.txt
collective.linkedin.egg-info/entry_points.txt
collective.linkedin.egg-info/namespace_packages.txt
collective.linkedin.egg-info/not-zip-safe
collective.linkedin.egg-info/paster_plugins.txt
collective.linkedin.egg-info/requires.txt
collective.linkedin.egg-info/top_level.txt
collective/linkedin/__init__.py
collective/linkedin/configure.zcml
collective/linkedin/overrides.zcml
collective/linkedin/profiles.zcml
collective/linkedin/setuphandlers.py
collective/linkedin/skins.zcml
collective/linkedin/tests.py
collective/linkedin/version.txt
collective/linkedin/browser/__init__.py
collective/linkedin/browser/company_info.py
collective/linkedin/browser/config.py
collective/linkedin/browser/configure.zcml
collective/linkedin/browser/interfaces.py
collective/linkedin/browser/overrides.zcml
collective/linkedin/browser/portlets.py
collective/linkedin/browser/profile_info.py
collective/linkedin/browser/viewlet.pt
collective/linkedin/browser/viewlets.py
collective/linkedin/browser/images/README.txt
collective/linkedin/browser/stylesheets/README.txt
collective/linkedin/browser/stylesheets/main.css
collective/linkedin/browser/templates/company_info.pt
collective/linkedin/browser/templates/linkedin_response.pt
collective/linkedin/browser/templates/profile_info.pt
collective/linkedin/browser/templates/site_actions.pt
collective/linkedin/profiles/default/actions.xml
collective/linkedin/profiles/default/collective.linkedin_various.txt
collective/linkedin/profiles/default/controlpanel.xml
collective/linkedin/profiles/default/cssregistry.xml
collective/linkedin/profiles/default/jsregistry.xml
collective/linkedin/profiles/default/metadata.xml
collective/linkedin/profiles/default/portlets.xml
collective/linkedin/profiles/default/skins.xml
collective/linkedin/profiles/default/viewlets.xml
collective/linkedin/skins/collective.linkedin_custom_templates/author.cpt
collective/linkedin/skins/collective.linkedin_custom_templates/author.cpt.metadata
collective/linkedin/skins/collective.linkedin_custom_templates/change_picture_helper.py
collective/linkedin/skins/collective.linkedin_custom_templates/getMemberLnProperties.py
