Metadata-Version: 1.0
Name: collective.linkedin
Version: 0.2.4
Summary: A Linked In integration for plone
Home-page: https://svn.plone.org/svn/collective/collective.linkedin/
Author: Javier Mansilla, Horacio Duran, Proteon, Machinalis
Author-email: jmansilla@machinalis.com, hduran@machinalis.com
License: GPL
Keywords: plone linkedin
Platform: UNKNOWN
Classifier: Framework :: Plone
Classifier: Programming Language :: Python
